quickstall/__about__.py
quickstall/__init__.py
quickstall/__main__.py
quickstall/cli/__init__.py
quickstall-0.0.1.dist-info/METADATA
quickstall-0.0.1.dist-info/WHEEL
quickstall-0.0.1.dist-info/entry_points.txt
quickstall-0.0.1.dist-info/licenses/LICENSE
quickstall-0.0.1.dist-info/RECORD
